aioyoomoney/__init__.py
aioyoomoney/authorize.py
aioyoomoney/exceptions.py
aioyoomoney/globals.py
aioyoomoney/utils.py
aioyoomoney/yoomoney.py
aioyoomoney/base/__init__.py
aioyoomoney/base/session.py
aioyoomoney/data_classes/__init__.py
aioyoomoney/data_classes/payment_status.py
aioyoomoney/schemas/__init__.py
aioyoomoney/schemas/account.py
aioyoomoney/schemas/operation_details.py
aioyoomoney/schemas/operation_history.py
aioyoomoney/schemas/quick_pay.py
aioyoomoney-0.1.0.dist-info/METADATA
aioyoomoney-0.1.0.dist-info/WHEEL
aioyoomoney-0.1.0.dist-info/top_level.txt
aioyoomoney-0.1.0.dist-info/RECORD
