Metadata-Version: 2.4
Name: aioyoomoney
Version: 0.1.0
Summary: Async YooMoney API Client
Author-email: belyankiss <belyankiss@gmail.com>
License-Expression: MIT
Requires-Python: >=3.9
Requires-Dist: aiohttp
Requires-Dist: pydantic
Requires-Dist: yarl
